edwh_sshkey_plugin/__about__.py
edwh_sshkey_plugin/__init__.py
edwh_sshkey_plugin/fabfile.py
edwh_sshkey_plugin-0.1.8.dist-info/METADATA
edwh_sshkey_plugin-0.1.8.dist-info/WHEEL
edwh_sshkey_plugin-0.1.8.dist-info/entry_points.txt
edwh_sshkey_plugin-0.1.8.dist-info/licenses/LICENSE.txt
edwh_sshkey_plugin-0.1.8.dist-info/RECORD
