Metadata-Version: 2.4
Name: edwh-sshkey-plugin
Version: 0.1.8
Summary: plugin for adding and removing keys to servers
Project-URL: Documentation, https://github.com/educationwarehouse/edwh-sshkey-plugin#readme
Project-URL: Issues, https://github.com/educationwarehouse/edwh-sshkey-plugin/issues
Project-URL: Source, https://github.com/educationwarehouse/edwh-sshkey-plugin
Author-email: Remco Boerma <remco.b@educationwarehouse.nl>, Sven Keimpema <sven.k@educationwarehouse.nl>, Romy Schöller <romy.s@educationwarehouse.nl>
License-Expression: MIT
License-File: LICENSE.txt
Classifier: Development Status :: 4 - Beta
Classifier: Programming Language :: Python
Classifier: Programming Language :: Python :: 3.10
Classifier: Programming Language :: Python :: 3.11
Classifier: Programming Language :: Python :: Implementation :: CPython
Classifier: Programming Language :: Python :: Implementation :: PyPy
Requires-Python: >=3.10
Requires-Dist: invoke
Provides-Extra: dev
Requires-Dist: black; extra == 'dev'
Requires-Dist: hatch; extra == 'dev'
